spokentxt_punctuation_restoration/__init__.py
spokentxt_punctuation_restoration/punctuation.py
spokentxt_punctuation_restoration-0.1.1.dist-info/METADATA
spokentxt_punctuation_restoration-0.1.1.dist-info/WHEEL
spokentxt_punctuation_restoration-0.1.1.dist-info/RECORD
