Metadata-Version: 2.3
Name: spokentxt-punctuation-restoration
Version: 0.1.1
Summary: 
Author: Jinwon Kim
Author-email: code.eric22@gmail.com
Requires-Python: >=3.11,<4.0
Classifier: Programming Language :: Python :: 3
Classifier: Programming Language :: Python :: 3.11
Classifier: Programming Language :: Python :: 3.12
Classifier: Programming Language :: Python :: 3.13
Requires-Dist: torch (>=2.1.0,<3.0.0)
Requires-Dist: transformers (>=4.49.0,<5.0.0)
